LICENSE.txt
MANIFEST.in
README.md
setup.py
humilis_stream_gtw/__init__.py
humilis_stream_gtw/meta.yaml.j2
humilis_stream_gtw/outputs.yaml.j2
humilis_stream_gtw/plugin.py
humilis_stream_gtw/resources.yaml.j2
humilis_stream_gtw.egg-info/PKG-INFO
humilis_stream_gtw.egg-info/SOURCES.txt
humilis_stream_gtw.egg-info/dependency_links.txt
humilis_stream_gtw.egg-info/entry_points.txt
humilis_stream_gtw.egg-info/not-zip-safe
humilis_stream_gtw.egg-info/requires.txt
humilis_stream_gtw.egg-info/top_level.txt