Metadata-Version: 2.1
Name: humilis-stream-gtw
Version: 1.3.0
Summary: Deploy an AWS API Gateway to Kinesis and/or Firehose
Home-page: https://github.com/humilis/humilis-stream-gtw
Author: German Gomez-Herrero, FindHotel BV
Author-email: german@findhotel.net
License: MIT
Platform: UNKNOWN
Classifier: Programming Language :: Python :: 3
License-File: LICENSE.txt
